deutschland/mudab/__init__.py
deutschland/mudab/api/__init__.py
deutschland/mudab/api/default_api.py
deutschland/mudab/api_client.py
deutschland/mudab/apis/__init__.py
deutschland/mudab/configuration.py
deutschland/mudab/exceptions.py
deutschland/mudab/model/__init__.py
deutschland/mudab/model/compartment.py
deutschland/mudab/model/filter.py
deutschland/mudab/model/filter_action.py
deutschland/mudab/model/filter_request.py
deutschland/mudab/model/helcom_plc_station.py
deutschland/mudab/model/list_mess_stationen200_response.py
deutschland/mudab/model/list_messwerte_plc200_response.py
deutschland/mudab/model/list_parameter200_response.py
deutschland/mudab/model/list_parameter_values200_response.py
deutschland/mudab/model/list_parameters_biologie200_response.py
deutschland/mudab/model/list_parameters_biota200_response.py
deutschland/mudab/model/list_parameters_plc200_response.py
deutschland/mudab/model/list_parameters_sediment200_response.py
deutschland/mudab/model/list_parameters_wasser200_response.py
deutschland/mudab/model/list_plc_stations200_response.py
deutschland/mudab/model/list_projekt_stationen200_response.py
deutschland/mudab/model/messstation.py
deutschland/mudab/model/messwert_plc.py
deutschland/mudab/model/orderby.py
deutschland/mudab/model/parameter.py
deutschland/mudab/model/parameter_plc.py
deutschland/mudab/model/parameter_value.py
deutschland/mudab/model/project_station.py
deutschland/mudab/model/range.py
deutschland/mudab/model_utils.py
deutschland/mudab/models/__init__.py
deutschland/mudab/rest.py
de_mudab-0.2.0.dist-info/METADATA
de_mudab-0.2.0.dist-info/WHEEL
de_mudab-0.2.0.dist-info/RECORD
